LICENSE
MANIFEST.in
NOTICE
README.md
requirements.txt
setup.py
MicroStark.egg-info/PKG-INFO
MicroStark.egg-info/SOURCES.txt
MicroStark.egg-info/dependency_links.txt
MicroStark.egg-info/entry_points.txt
MicroStark.egg-info/not-zip-safe
MicroStark.egg-info/requires.txt
MicroStark.egg-info/top_level.txt
stark/__init__.py
stark/cli.py
stark/client.py
stark/constants.py
stark/default_settings.py
stark/env.py
stark/logger.py
stark/settings.py
stark/decorators/__init__.py
stark/decorators/admins.py
stark/decorators/callback.py
stark/decorators/command.py
stark/decorators/extras.py
stark/decorators/inline.py
stark/plugins/constants.py
stark/plugins/helpers.py
stark/plugins/addons/about.py
stark/plugins/addons/bans.py
stark/plugins/addons/broadcast.py
stark/plugins/addons/buttons.py
stark/plugins/addons/help.py
stark/plugins/addons/id.py
stark/plugins/addons/json.py
stark/plugins/addons/start.py
stark/plugins/addons/stats.py
stark/plugins/addons/sudo.py
stark/types/__init__.py
stark/types/chat.py
stark/types/dict.py
stark/types/message.py
stark/types/permissions.py
stark/types/settings.py
stark/types/user.py
stark/utils/__init__.py
stark/utils/conversion.py
stark/utils/file.py
stark/utils/filters.py
stark/utils/paste.py
stark/utils/patch.py
stark/utils/process.py
stark/utils/pyrogress.py
stark/utils/requests.py
stark/utils/stickers.py